bankr/__about__.py
bankr/__init__.py
bankr/__main__.py
bankr/app_01-balance.py
bankr/app_02-income.py
bankr/bankr.sample.yaml
bankr/calc.py
bankr/files.py
bankr/money.py
bankr/tuiplot.py
bankr/tuitable.py
bankr/utils.py
bankr/cli/__init__.py
bankr/cli/commands.py
bankr/cli/locale/cats.de.yml
bankr/cli/locale/cats.en.yml
bankr/cli/locale/general.de.yml
bankr/cli/locale/general.en.yml
bankr/data.sample/accounts.yaml
bankr/data.sample/book-v1.pickle
bankr/data.sample/book-v1.yaml
bankr/data.sample/cats.yaml
bankr/data.sample/filters.yaml
bankr/data.sample/csv/13441.yaml
bankr/data.sample/csv/38726777.yaml
bankr/data.sample/csv/DE72387267777958538073-20250110.csv
bankr/data.sample/csv/FR591344114241SLXBUAHDY9806-20250110.csv
bankr/data.sample/csv/GB71RJKT75252048811544-20250110.csv
bankr/data.sample/csv/RJKT.yaml
bankr/data.sample/csv/bankcode.sample.yaml
bankr-0.0.2.dist-info/METADATA
bankr-0.0.2.dist-info/WHEEL
bankr-0.0.2.dist-info/entry_points.txt
bankr-0.0.2.dist-info/licenses/LICENSE.txt
bankr-0.0.2.dist-info/RECORD
