Metadata-Version: 2.4
Name: bankr
Version: 0.0.2
Summary: Simple Python code for your Bank Accounting
Project-URL: Documentation, https://rokor.codeberg.page/bankr
Project-URL: Issues, https://codeberg.org/rokor/bankr/issues
Project-URL: Source, https://codeberg.org/rokor/bankr
Author-email: Robert Kormann <rokor@kormann.info>
License-Expression: Unlicense
License-File: LICENSE.txt
Keywords: account,accounting,bank,banking,pandas,panel
Classifier: Development Status :: 3 - Alpha
Classifier: Environment :: Console
Classifier: Intended Audience :: End Users/Desktop
Classifier: License :: OSI Approved :: The Unlicense (Unlicense)
Classifier: Programming Language :: Python
Classifier: Programming Language :: Python :: 3.12
Classifier: Programming Language :: Python :: 3.13
Classifier: Programming Language :: Python :: Implementation :: CPython
Requires-Python: >=3.12
Requires-Dist: click
Requires-Dist: inquirer
Requires-Dist: pandas
Requires-Dist: plotext
Requires-Dist: prettytable
Requires-Dist: pyaml
Requires-Dist: pyfiglet
Requires-Dist: python-i18n
Requires-Dist: schwifty
